mnist1d/__init__.py
mnist1d/data.py
mnist1d/transform.py
mnist1d/utils.py
mnist1d-0.0.2.post1.dist-info/LICENSE
mnist1d-0.0.2.post1.dist-info/METADATA
mnist1d-0.0.2.post1.dist-info/WHEEL
mnist1d-0.0.2.post1.dist-info/top_level.txt
mnist1d-0.0.2.post1.dist-info/RECORD
