Metadata-Version: 2.1
Name: mnist1d
Version: 0.0.2.post1
Summary: A 1D analogue of the MNIST dataset for measuring spatial biases and answering Science of Deep Learning questions
Author-email: Sam Greydanus <greydanus@users.noreply.github.com>, Peter Steinbach <psteinb@users.noreply.github.com>, Karim <karim-53@users.noreply.github.com>, Dmitry Kobak <dmitry.kobak@uni-tuebingen.de>, Jakob Jordan <jakobjordan@posteo.de>
License: Apache-2.0
Project-URL: Homepage, https://github.com/greydanus/mnist1d
Keywords: dataset,mnist,machine learning,deep learning,1D
Classifier: License :: OSI Approved :: Apache Software License
Classifier: Programming Language :: Python
Classifier: Programming Language :: Python :: 3
Classifier: Programming Language :: Python :: 3.7
Classifier: Programming Language :: Python :: 3.8
Classifier: Programming Language :: Python :: 3.9
Classifier: Programming Language :: Python :: 3.10
Classifier: Programming Language :: Python :: 3.11
Classifier: Topic :: Scientific/Engineering :: Artificial Intelligence
Classifier: Intended Audience :: Science/Research
Requires-Python: >=3.7
License-File: LICENSE
Requires-Dist: requests
Requires-Dist: numpy
Requires-Dist: matplotlib
Requires-Dist: scipy
Provides-Extra: dev
Requires-Dist: pytest; extra == "dev"
Provides-Extra: all
Requires-Dist: torch; extra == "all"
Requires-Dist: notebook; extra == "all"
